expertsystem/__init__.py
expertsystem/py.typed
expertsystem/amplitude/__init__.py
expertsystem/amplitude/_graph_info.py
expertsystem/amplitude/data.py
expertsystem/amplitude/helicity.py
expertsystem/amplitude/kinematics.py
expertsystem/amplitude/dynamics/__init__.py
expertsystem/amplitude/dynamics/builder.py
expertsystem/amplitude/dynamics/lineshape.py
expertsystem/io/__init__.py
expertsystem/io/_dict.py
expertsystem/io/_dot.py
expertsystem/reaction/__init__.py
expertsystem/reaction/_system_control.py
expertsystem/reaction/additional_definitions.yml
expertsystem/reaction/argument_handling.py
expertsystem/reaction/combinatorics.py
expertsystem/reaction/conservation_rules.py
expertsystem/reaction/default_settings.py
expertsystem/reaction/particle-validation.json
expertsystem/reaction/particle.py
expertsystem/reaction/quantum_numbers.py
expertsystem/reaction/solving.py
expertsystem/reaction/topology.py
expertsystem/reaction/transition.py
expertsystem-0.7.3.dist-info/METADATA
expertsystem-0.7.3.dist-info/WHEEL
expertsystem-0.7.3.dist-info/top_level.txt
expertsystem-0.7.3.dist-info/RECORD
