Metadata-Version: 2.1
Name: expertsystem
Version: 0.7.3
Summary: UNKNOWN
Home-page: UNKNOWN
Author: Common Partial Wave Analysis
Author-email: compwa-admin@ep1.rub.de
Maintainer-email: compwa-admin@ep1.rub.de
License: GPLv3 or later
Project-URL: Tracker, https://github.com/ComPWA/expertsystem/issues
Project-URL: Changelog, https://github.com/ComPWA/expertsystem/releases
Project-URL: Documentation, https://expertsystem.rtfd.io
Project-URL: Source, https://github.com/ComPWA/expertsystem
Keywords: HEP,PWA,amplitude analysis,partial wave analysis,particle physics,particles,physics
Platform: UNKNOWN
Classifier: Development Status :: 4 - Beta
Classifier: Intended Audience :: Developers
Classifier: Intended Audience :: Education
Classifier: Intended Audience :: Science/Research
Classifier: License :: OSI Approved :: GNU General Public License v3 or later (GPLv3+)
Classifier: Natural Language :: English
Classifier: Operating System :: OS Independent
Classifier: Programming Language :: Python
Classifier: Programming Language :: Python :: 3.6
Classifier: Programming Language :: Python :: 3.7
Classifier: Programming Language :: Python :: 3.8
Classifier: Programming Language :: Python :: 3.9
Classifier: Topic :: Scientific/Engineering
Classifier: Topic :: Scientific/Engineering :: Physics
Classifier: Typing :: Typed
Requires-Python: <3.10,>=3.6
Requires-Dist: attrs (>=20.1.0)
Requires-Dist: jsonschema
Requires-Dist: numpy (>=1.16)
Requires-Dist: particle
Requires-Dist: python-constraint
Requires-Dist: PyYAML
Requires-Dist: sympy
Requires-Dist: tqdm (>=4.24.0)
Requires-Dist: typing-extensions ; python_version < "3.8.0"
Provides-Extra: viz
Requires-Dist: graphviz ; extra == 'viz'
